prefect_mcp_server/__init__.py
prefect_mcp_server/__main__.py
prefect_mcp_server/middleware.py
prefect_mcp_server/py.typed
prefect_mcp_server/server.py
prefect_mcp_server/settings.py
prefect_mcp_server/types.py
prefect_mcp_server/_prefect_client/__init__.py
prefect_mcp_server/_prefect_client/automations.py
prefect_mcp_server/_prefect_client/client.py
prefect_mcp_server/_prefect_client/dashboard.py
prefect_mcp_server/_prefect_client/deployments.py
prefect_mcp_server/_prefect_client/events.py
prefect_mcp_server/_prefect_client/flow_runs.py
prefect_mcp_server/_prefect_client/flows.py
prefect_mcp_server/_prefect_client/identity.py
prefect_mcp_server/_prefect_client/rate_limits.py
prefect_mcp_server/_prefect_client/task_runs.py
prefect_mcp_server/_prefect_client/work_pools.py
prefect_mcp-0.0.1b9.dist-info/METADATA
prefect_mcp-0.0.1b9.dist-info/WHEEL
prefect_mcp-0.0.1b9.dist-info/entry_points.txt
prefect_mcp-0.0.1b9.dist-info/RECORD
