Metadata-Version: 2.4
Name: prefect-mcp
Version: 0.0.1b9
Summary: MCP server for interacting with Prefect
Author-email: Prefect Technologies <help@prefect.io>
Requires-Python: >=3.10
Requires-Dist: fastmcp>=2.12.3
Requires-Dist: prefect>=3.4.22
Provides-Extra: logfire
Requires-Dist: logfire; extra == 'logfire'
